Metadata-Version: 1.1
Name: enumr
Version: 1.0
Summary: Ranged enumeration data type
Home-page: https://github.com/xoiss/python-enumr
Author: Alexander A. Strelets
Author-email: StreletsAA@gmail.com
License: Public Domain
Download-URL: https://github.com/xoiss/python-enumr
Platform: Linux
Classifier: Development Status :: 3 - Alpha
Classifier: Intended Audience :: Developers
Classifier: License :: CC0 1.0 Universal (CC0 1.0) Public Domain Dedication
Classifier: Natural Language :: English
Classifier: Operating System :: POSIX :: Linux
Classifier: Programming Language :: Python :: 2.7
Classifier: Topic :: Software Development :: Libraries :: Python Modules
